django_globus_portal_framework-0.4.15.dist-info/licenses/LICENSE
globus_portal_framework/__init__.py
globus_portal_framework/api.py
globus_portal_framework/apps.py
globus_portal_framework/auth.py
globus_portal_framework/checks.py
globus_portal_framework/constants.py
globus_portal_framework/context_processors.py
globus_portal_framework/exc.py
globus_portal_framework/gclients.py
globus_portal_framework/gsearch.py
globus_portal_framework/gtransfer.py
globus_portal_framework/middleware.py
globus_portal_framework/settings.py
globus_portal_framework/urls.py
globus_portal_framework/urls_debugging.py
globus_portal_framework/version.py
globus_portal_framework/data/datacite.json
globus_portal_framework/modifiers/__init__.py
globus_portal_framework/modifiers/facets.py
globus_portal_framework/search/__init__.py
globus_portal_framework/search/apps.py
globus_portal_framework/static/bootstrap/css/bootstrap-grid.css
globus_portal_framework/static/bootstrap/css/bootstrap-grid.css.map
globus_portal_framework/static/bootstrap/css/bootstrap-grid.min.css
globus_portal_framework/static/bootstrap/css/bootstrap-grid.min.css.map
globus_portal_framework/static/bootstrap/css/bootstrap-reboot.css
globus_portal_framework/static/bootstrap/css/bootstrap-reboot.css.map
globus_portal_framework/static/bootstrap/css/bootstrap-reboot.min.css
globus_portal_framework/static/bootstrap/css/bootstrap-reboot.min.css.map
globus_portal_framework/static/bootstrap/css/bootstrap.css
globus_portal_framework/static/bootstrap/css/bootstrap.css.map
globus_portal_framework/static/bootstrap/css/bootstrap.min.css
globus_portal_framework/static/bootstrap/css/bootstrap.min.css.map
globus_portal_framework/static/bootstrap/js/bootstrap.bundle.js
globus_portal_framework/static/bootstrap/js/bootstrap.bundle.js.map
globus_portal_framework/static/bootstrap/js/bootstrap.bundle.min.js
globus_portal_framework/static/bootstrap/js/bootstrap.bundle.min.js.map
globus_portal_framework/static/bootstrap/js/bootstrap.js
globus_portal_framework/static/bootstrap/js/bootstrap.js.map
django_globus_portal_framework-0.4.15.dist-info/METADATA
django_globus_portal_framework-0.4.15.dist-info/WHEEL
django_globus_portal_framework-0.4.15.dist-info/top_level.txt
django_globus_portal_framework-0.4.15.dist-info/RECORD
