Metadata-Version: 2.4
Name: django-globus-portal-framework
Version: 0.4.15
Summary: A framework for collating Globus Search data for use with various Globus services. 
Home-page: https://github.com/globus/django-globus-portal-framework
Author: Globus Team
Author-email: support@globus.org
License: apache 2.0
Keywords: globus,django
Classifier: Intended Audience :: Developers
Classifier: License :: OSI Approved :: Apache Software License
Classifier: Operating System :: POSIX
Classifier: Programming Language :: Python
Classifier: Programming Language :: Python :: 3.8
Classifier: Programming Language :: Python :: 3.9
Classifier: Programming Language :: Python :: 3.10
Classifier: Programming Language :: Python :: 3.11
Classifier: Programming Language :: Python :: 3.12
Classifier: Programming Language :: Python :: 3.13
Classifier: Topic :: Communications :: File Sharing
Classifier: Topic :: Internet :: WWW/HTTP
Classifier: Topic :: Software Development :: Libraries :: Python Modules
License-File: LICENSE
Requires-Dist: django<6
Requires-Dist: globus_sdk<4,>=3
Requires-Dist: social-auth-app-django<6.0.0,>=3.0.0
Requires-Dist: python-jose[cryptography]>=3.0.1
Requires-Dist: packaging>=21.0
Dynamic: author
Dynamic: author-email
Dynamic: classifier
Dynamic: description
Dynamic: description-content-type
Dynamic: home-page
Dynamic: keywords
Dynamic: license
Dynamic: license-file
Dynamic: requires-dist
Dynamic: summary
